plumelog_loguru/__init__.py
plumelog_loguru/config.py
plumelog_loguru/extractor.py
plumelog_loguru/models.py
plumelog_loguru/redis_client.py
plumelog_loguru/redis_sink.py
plumelog_loguru-0.2.1.dist-info/METADATA
plumelog_loguru-0.2.1.dist-info/WHEEL
plumelog_loguru-0.2.1.dist-info/RECORD
