Metadata-Version: 2.4
Name: plumelog-loguru
Version: 0.2.1
Summary: Plumelog集成库，为Loguru提供Redis日志传输功能
Project-URL: Homepage, https://github.com/CodingOX/plumelog-loguru
Project-URL: Repository, https://github.com/CodingOX/plumelog-loguru.git
Project-URL: Issues, https://github.com/CodingOX/plumelog-loguru/issues
Author-email: Alistar Max <codingox@gmail.com>
License: Apache-2.0
Keywords: async,logging,loguru,plumelog,redis
Classifier: Development Status :: 4 - Beta
Classifier: Intended Audience :: Developers
Classifier: License :: OSI Approved :: Apache Software License
Classifier: Programming Language :: Python :: 3
Classifier: Programming Language :: Python :: 3.10
Classifier: Programming Language :: Python :: 3.11
Classifier: Programming Language :: Python :: 3.12
Classifier: Topic :: Software Development :: Libraries :: Python Modules
Classifier: Topic :: System :: Logging
Requires-Python: >=3.10
Requires-Dist: loguru>=0.7.0
Requires-Dist: pydantic-settings>=2.11.0
Requires-Dist: pydantic>=2.11.9
Requires-Dist: redis[hiredis]>=5.0.0
Provides-Extra: dev
Requires-Dist: black>=23.0.0; extra == 'dev'
Requires-Dist: build>=0.10.0; extra == 'dev'
Requires-Dist: isort>=5.12.0; extra == 'dev'
Requires-Dist: mypy>=1.18.2; extra == 'dev'
Requires-Dist: pytest-asyncio>=0.21.0; extra == 'dev'
Requires-Dist: pytest-cov>=7.0.0; extra == 'dev'
Requires-Dist: pytest>=8.4.2; extra == 'dev'
Requires-Dist: ruff>=0.13.1; extra == 'dev'
Requires-Dist: twine>=6.2.0; extra == 'dev'
